[
  {
    "title": "Software Engineer Intern",
    "org": "The Chokka Center",
    "orgLink": "https://chokkacenter.com/",
    "src": "/chokka.png",
    "description": [
      "Designed and implemented a microservice using Node.js and Express.js to analyze, predict, and measure patient mental health severity from questionnaire responses.",
      "Collaborated on critical projects, resolving high-priority bugs and introducing new features to improve reliability and user experience for patients and doctors.",
      "Optimized data storage in a NoSQL database, reducing storage and processing overhead by 40–45%, resulting in increased system efficiency.",
      "Authored comprehensive developer documentation, including API references, architectural diagrams, and onboarding guides, to support knowledge sharing and streamline maintenance efforts."
    ],
    "skills": [
      {
        "iconName": "Vue.Js",
        "hyperlink": "https://vuejs.org/"
      },
      {
        "iconName": "BootstrapVue",
        "hyperlink": "https://bootstrap-vue.org/"
      },
      {
        "iconName": "MongoDB",
        "hyperlink": "https://www.mongodb.com/"
      },
      {
        "iconName": "Microservice",
        "hyperlink": "https://learn.microsoft.com/en-us/azure/architecture/guide/architecture-styles/microservices"
      },
      {
        "iconName": "Postgresql",
        "hyperlink": "https://www.postgresql.org/"
      },
      {
        "iconName": "Express",
        "hyperlink": "https://expressjs.com/"
      },
      {
        "iconName": "NodeJs",
        "hyperlink": "https://nodejs.org/en"
      },
      {
        "iconName": "NGINX",
        "hyperlink": "https://nginx.org/en/"
      },
      {
        "iconName": "Python",
        "hyperlink": "https://www.python.org/"
      },
      {
        "iconName": "MachineLearning",
        "hyperlink": "https://en.wikipedia.org/wiki/Machine_learning"
      }
    ]
  },
  {
    "title": "Associate Software Engineer - I",
    "org": "Highradius Technologies",
    "orgLink": "https://www.highradius.com/",
    "src": "/hrc2.png",
    "description": [
      "Architected and implemented over 50 user stories and resolved 150+ bugs for payment-based web applications using React, ExtJS, Java Spring Boot, and JPA.",
      "Served as Scrum Master for six months, leading Scrum meetings and enforcing Agile practices to enhance team productivity.",
      "Optimized REST API interactions with SQL server databases, reducing resource overhead and achieving a 60% improvement in system performance, including faster API response times and lower cloud processor usage.",
      "Led the migration of B2B SaaS virtual card payment systems from legacy technologies (Spring MVC, Hibernate, ExtJS) to a modern stack with React and Spring Boot, integrating Java web services for seamless inter-application communication.",
      "Introduced JUnit testing for backend projects and conducted training sessions to educate developers on testing best practices and quality assurance."
    ],
    "skills": [
      {
        "iconName": "Java",
        "hyperlink": "https://www.java.com/en/"
      },
      {
        "iconName": "Spring_Boot",
        "hyperlink": "https://spring.io/projects/spring-boot"
      },
      {
        "iconName": "Junit",
        "hyperlink": "https://junit.org/junit5/"
      },
      {
        "iconName": "Typescript",
        "hyperlink": "https://www.typescriptlang.org/"
      },
      {
        "iconName": "React.Js",
        "hyperlink": "https://react.dev/"
      },
      {
        "iconName": "Redux",
        "hyperlink": "https://redux.js.org/"
      },
      {
        "iconName": "Git",
        "hyperlink": "https://git-scm.com/"
      },
      {
        "iconName": "Agile",
        "hyperlink": "https://www.atlassian.com/agile"
      },
      {
        "iconName": "Jira",
        "hyperlink": "https://www.atlassian.com/software/jira"
      },
      {
        "iconName": "Python",
        "hyperlink": "https://www.python.org/"
      },
      {
        "iconName": "ExtJs",
        "hyperlink": "https://www.sencha.com/products/extjs/"
      },
      {
        "iconName": "Postgresql",
        "hyperlink": "https://www.postgresql.org/"
      },
      {
        "iconName": "Docker",
        "hyperlink": "https://www.docker.com/"
      },
      {
        "iconName": "Cicd",
        "hyperlink": "https://about.gitlab.com/topics/ci-cd/"
      }
    ]
  },
  {
    "title": "Software Developer Intern",
    "org": "Highradius Technologies",
    "orgLink": "https://www.highradius.com/",
    "src": "/Company-Overview-OG.png",
    "description": [
      "Developed a full-stack web application using React, SQL, and JDBC to streamline invoice management for B2B sellers.",
      "Implemented key features such as tracking invoice statuses (paid, rejected, delayed), initiating disputes, and maintaining payment histories to enhance financial workflows.",
      "Collaborated with client data to design a machine learning model that predicts customer churn and estimates accounts receivable based on historical credit purchase data.",
      "Enabled businesses to make data-driven decisions and improve financial planning through predictive insights on customer behavior and payment trends."
    ],
    "skills": [
      {
        "iconName": "Python",
        "hyperlink": "https://www.python.org/"
      },
      {
        "iconName": "Java",
        "hyperlink": "https://www.java.com/en/"
      },
      {
        "iconName": "Typescript",
        "hyperlink": "https://www.typescriptlang.org/"
      },
      {
        "iconName": "React.Js",
        "hyperlink": "https://react.dev/"
      },
      {
        "iconName": "Redux",
        "hyperlink": "https://redux.js.org/"
      },
      {
        "iconName": "MachineLearning",
        "hyperlink": "https://en.wikipedia.org/wiki/Machine_learning"
      }
    ]
  }
]
